sievemgr.py
sievemgr-0.7.4.7.dist-info/LICENSE.rst
sievemgr-0.7.4.7.dist-info/METADATA
sievemgr-0.7.4.7.dist-info/WHEEL
sievemgr-0.7.4.7.dist-info/entry_points.txt
sievemgr-0.7.4.7.dist-info/top_level.txt
sievemgr-0.7.4.7.dist-info/RECORD
