Metadata-Version: 2.1
Name: sievemgr
Version: 0.7.4.7
Summary: Fully-featured ManageSieve command-line client and library
Author: Odin Kroeger
Project-URL: homepage, https://odkr.codeberg.page/sievemgr
Project-URL: repository, https://codeberg.org/odkr/sievemgr
Project-URL: issues, https://github.com/odkr/sievemgr/issues
Keywords: managesieve,sieve,mail,filter
Classifier: Development Status :: 4 - Beta
Classifier: Environment :: Console
Classifier: Intended Audience :: End Users/Desktop
Classifier: Intended Audience :: System Administrators
Classifier: License :: OSI Approved :: GNU General Public License v3 or later (GPLv3+)
Classifier: Programming Language :: Python :: 3 :: Only
Classifier: Programming Language :: Python :: 3.9
Classifier: Programming Language :: Python :: 3.10
Classifier: Programming Language :: Python :: 3.11
Classifier: Programming Language :: Python :: 3.12
Classifier: Programming Language :: Python :: 3.13
Classifier: Natural Language :: English
Classifier: Operating System :: POSIX
Classifier: Topic :: Communications :: Email :: Filters
Requires-Python: >=3.9
License-File: LICENSE.rst
Requires-Dist: dnspython >=2
Requires-Dist: cryptography >=2.4
